setup.py
iosapplist/__init__.py
iosapplist/__main__.py
iosapplist/app.py
iosapplist/applist.py
iosapplist/container.py
iosapplist.egg-info/PKG-INFO
iosapplist.egg-info/SOURCES.txt
iosapplist.egg-info/dependency_links.txt
iosapplist.egg-info/entry_points.txt
iosapplist.egg-info/requires.txt
iosapplist.egg-info/top_level.txt
iosapplist/cli/__init__.py
iosapplist/cli/__main__.py
iosapplist/cli/commands/__init__.py
iosapplist/cli/commands/list.py
iosapplist/cli/commands/python_repl.py
iosapplist/cli/commands/refresh.py
iosapplist/cli/commands/shell.py
iosapplist/cli/engine/__init__.py
iosapplist/cli/engine/cli.py
iosapplist/cli/engine/command.py
iosapplist/cli/engine/commandlist.py
iosapplist/cli/engine/output.py
iosapplist/cli/engine/commands/__init__.py
iosapplist/cli/engine/commands/python_repl.py
iosapplist/cli/engine/commands/shell.py
iosapplist/util/__init__.py
iosapplist/util/propertylist.py